microsoft/teams/mcpplugin/__init__.py
microsoft/teams/mcpplugin/ai_plugin.py
microsoft/teams/mcpplugin/server_plugin.py
microsoft/teams/mcpplugin/transport.py
microsoft/teams/mcpplugin/models/__init__.py
microsoft/teams/mcpplugin/models/cache.py
microsoft/teams/mcpplugin/models/params.py
microsoft/teams/mcpplugin/models/tool.py
microsoft_teams_mcpplugin-2.0.0a5.dist-info/METADATA
microsoft_teams_mcpplugin-2.0.0a5.dist-info/WHEEL
microsoft_teams_mcpplugin-2.0.0a5.dist-info/RECORD
